mdx_truly_sane_lists/__init__.py
mdx_truly_sane_lists/mdx_truly_sane_lists.py
mdx_truly_sane_lists/tests.py
mdx_truly_sane_lists-1.3.dist-info/LICENSE
mdx_truly_sane_lists-1.3.dist-info/METADATA
mdx_truly_sane_lists-1.3.dist-info/WHEEL
mdx_truly_sane_lists-1.3.dist-info/top_level.txt
mdx_truly_sane_lists-1.3.dist-info/RECORD
