Metadata-Version: 2.1
Name: mdx_truly_sane_lists
Version: 1.3
Summary: Extension for Python-Markdown that makes lists truly sane. Custom indents for nested lists and fix for messy linebreaks.
Home-page: https://github.com/radude/mdx_truly_sane_lists
Author: radude
Author-email: admin@rentry.co
License: MIT
Keywords: markdown extension,markup,lists,markdown
Classifier: Topic :: Text Processing :: Markup
Classifier: Topic :: Text Processing :: Markup :: Markdown
Classifier: Topic :: Utilities
Classifier: Programming Language :: Python :: 3.3
Classifier: Programming Language :: Python :: 3.4
Classifier: Programming Language :: Python :: 3.5
Classifier: Programming Language :: Python :: 3.6
Classifier: Programming Language :: Python :: 3.7
Classifier: Programming Language :: Python :: 3.8
Classifier: Programming Language :: Python :: 3.9
Classifier: Programming Language :: Python :: 3.10
Classifier: License :: OSI Approved :: MIT License
License-File: LICENSE
